deep_dance/__init__.py
deep_dance/__main__.py
deep_dance/client/__init__.py
deep_dance/client/commands/__init__.py
deep_dance/client/commands/commands.py
deep_dance/client/dance_application.py
deep_dance-0.2.0.dist-info/entry_points.txt
deep_dance-0.2.0.dist-info/WHEEL
deep_dance-0.2.0.dist-info/METADATA
deep_dance-0.2.0.dist-info/RECORD
