Metadata-Version: 2.1
Name: deep-dance
Version: 0.2.0
Summary: 
Author: AeRabelais
Author-email: pantagruelspendulum@protonmail.com
Requires-Python: >=3.9,<4.0
Classifier: Programming Language :: Python :: 3
Classifier: Programming Language :: Python :: 3.10
Classifier: Programming Language :: Python :: 3.9
Requires-Dist: cleo (>=0.8.1,<0.9.0)
